redmine_gitlab_migrator/__init__.py
redmine_gitlab_migrator/commands.py
redmine_gitlab_migrator/converters.py
redmine_gitlab_migrator/gitlab.py
redmine_gitlab_migrator/logger.py
redmine_gitlab_migrator/redmine.py
redmine_gitlab_migrator/sql.py
redmine_gitlab_migrator/wiki.py
redmine_gitlab_migrator-1.0.3.dist-info/LICENSE
redmine_gitlab_migrator-1.0.3.dist-info/METADATA
redmine_gitlab_migrator-1.0.3.dist-info/WHEEL
redmine_gitlab_migrator-1.0.3.dist-info/entry_points.txt
redmine_gitlab_migrator-1.0.3.dist-info/top_level.txt
redmine_gitlab_migrator-1.0.3.dist-info/RECORD
