Metadata-Version: 2.1
Name: redmine-gitlab-migrator
Version: 1.0.3
Summary: Migrate a redmine project to gitlab
Home-page: https://github.com/redmine-gitlab-migrator/redmine-gitlab-migrator
Author: Jocelyn Delalande
Author-email: jdelalande@oasiswork.fr
License: GPL
Platform: UNKNOWN
Classifier: License :: OSI Approved :: GNU General Public License v3 (GPLv3)
Requires-Dist: pyyaml
Requires-Dist: requests
Requires-Dist: GitPython
Requires-Dist: pypandoc
